LICENSE
MANIFEST.in
README.rst
setup.cfg
setup.py
shell.ini
examples/hello_world.py
tangled.web.egg-info/PKG-INFO
tangled.web.egg-info/SOURCES.txt
tangled.web.egg-info/dependency_links.txt
tangled.web.egg-info/entry_points.txt
tangled.web.egg-info/requires.txt
tangled.web.egg-info/top_level.txt
tangled/web/__init__.py
tangled/web/abcs.py
tangled/web/app.py
tangled/web/const.py
tangled/web/cors.py
tangled/web/csrf.py
tangled/web/defaults.ini
tangled/web/events.py
tangled/web/exc.py
tangled/web/handlers.py
tangled/web/representations.py
tangled/web/request.py
tangled/web/response.py
tangled/web/settings.py
tangled/web/static.py
tangled/web/resource/__init__.py
tangled/web/resource/config.py
tangled/web/resource/mounted.py
tangled/web/resource/resource.py
tangled/web/scaffolds/__init__.py
tangled/web/scaffolds/basic/development.ini
tangled/web/scaffolds/basic/setup.py
tangled/web/scaffolds/basic/__package__/__init__.py
tangled/web/scaffolds/basic/__package__/resources.py
tangled/web/scaffolds/basic/__package__/tests/__init__.py
tangled/web/scripts/__init__.py
tangled/web/scripts/actions.py
tangled/web/scripts/mixins.py
tangled/web/scripts/serve.py
tangled/web/scripts/shell.py
tangled/web/scripts/show.py
tangled/web/tests/__init__.py
tangled/web/tests/test_app.py
tangled/web/tests/test_handlers.py
tangled/web/tests/test_resource/__init__.py
tangled/web/tests/test_resource/test_config.py
tangled/web/tests/test_resource/test_mounted.py