Metadata-Version: 1.1
Name: tangled.web
Version: 1.0a12
Summary: RESTful Web Framework
Home-page: http://tangledframework.org/
Author: Wyatt Baldwin
Author-email: self@wyattbaldwin.com
License: UNKNOWN
Download-URL: https://github.com/TangledWeb/tangled.web/tags
Platform: UNKNOWN
Classifier: Development Status :: 3 - Alpha
Classifier: Environment :: Web Environment
Classifier: Intended Audience :: Developers
Classifier: License :: OSI Approved :: MIT License
Classifier: Programming Language :: Python :: 3
Classifier: Programming Language :: Python :: 3.3
Classifier: Programming Language :: Python :: 3.4
Classifier: Programming Language :: Python :: 3.5
